Metadata-Version: 2.1
Name: gfc
Version: 0.0.3
Summary: A python library for geodesy research
Home-page: UNKNOWN
Author: Li Zhen
Author-email: hpulizhen@163.com
License: UNKNOWN
Keywords: GNSS SLR orbit determination positioning POD
Platform: UNKNOWN
Classifier: Development Status :: 3 - Alpha
Classifier: License :: OSI Approved :: MIT License
Classifier: Programming Language :: Python :: 3.6
